cordslash/__init__.py
cordslash/client.py
cordslash/command.py
cordslash/context.py
cordslash/models.py
cordslash-0.1.3.dist-info/LICENSE
cordslash-0.1.3.dist-info/METADATA
cordslash-0.1.3.dist-info/WHEEL
cordslash-0.1.3.dist-info/top_level.txt
cordslash-0.1.3.dist-info/RECORD
