Metadata-Version: 2.1
Name: cordslash
Version: 0.1.3
Summary: A small slash commands wrapper for discord
Home-page: https://github.com/an-dyy/cordslash
Author: an-dyy
Author-email: yrisxl@gmail.com
License: UNKNOWN
Project-URL: Bug Tracker, https://github.com/an-dyy/cordslash/issues
Platform: UNKNOWN
Classifier: Programming Language :: Python :: 3
Classifier: License :: OSI Approved :: MIT License
Classifier: Operating System :: OS Independent
Requires-Python: >=3.8
License-File: LICENSE
